MANIFEST.in
README.md
__version__
setup.cfg
setup.py
chapter/__init__.py
chapter/one.py
nurbs_algorithms.egg-info/PKG-INFO
nurbs_algorithms.egg-info/SOURCES.txt
nurbs_algorithms.egg-info/dependency_links.txt
nurbs_algorithms.egg-info/requires.txt
nurbs_algorithms.egg-info/top_level.txt