Metadata-Version: 1.1
Name: nurbs-algorithms
Version: 1.0.1
Summary: nurbs-algorithms
Home-page: https://github.com/jeffrey-cochran/nurbs-algorithms
Author: Jeff Cochran
Author-email: jeffrey.david.cochran@gmail.com
License: UNKNOWN
Download-URL: https://github.com/jeffrey-cochran/nurbs-algorithms/archive/1.0.1.tar.gz
Keywords: NURBS
Platform: UNKNOWN
Classifier: Development Status :: 3 - Alpha
Classifier: License :: OSI Approved :: MIT License
Classifier: Operating System :: Microsoft :: Windows
Classifier: Programming Language :: Python :: 3.6
